dpkits/__init__.py
dpkits/ap_data_converter.py
dpkits/calculate_lsm.py
dpkits/codeframe_reader.py
dpkits/data_analysis.py
dpkits/data_processing.py
dpkits/data_transpose.py
dpkits/logging.py
dpkits/table_formater.py
dpkits/table_formater_v2.py
dpkits/table_generator.py
dpkits/table_generator_v2.py
dpkits/Tabulation/model_data2run.py
dpkits/Tabulation/model_question.py
dpkits/Tabulation/model_side_qres.py
dpkits/Tabulation/model_table.py
dpkits/Tabulation/table_horizontal.py
dpkits/Tabulation/table_vertical.py
dpkits/Tabulation/tabulation.py
dpkits-1.6.4.dist-info/licenses/LICENSE
dpkits-1.6.4.dist-info/METADATA
dpkits-1.6.4.dist-info/WHEEL
dpkits-1.6.4.dist-info/top_level.txt
dpkits-1.6.4.dist-info/RECORD
