Metadata-Version: 2.4
Name: dpkits
Version: 1.6.4
Summary: A small package for data processing
Author-email: Hung Dao <hung.daotuan.1991@gmail.com>
Project-URL: Homepage, https://github.com/HungDaoHD/packaging_dpkits
Project-URL: Bug Tracker, https://github.com/HungDaoHD/packaging_dpkits/issues
Classifier: Programming Language :: Python :: 3
Classifier: License :: OSI Approved :: MIT License
Classifier: Operating System :: OS Independent
Requires-Python: >=3.9
License-File: LICENSE
Requires-Dist: colorama
Requires-Dist: contourpy
Requires-Dist: cycler
Requires-Dist: et-xmlfile
Requires-Dist: fonttools
Requires-Dist: joblib
Requires-Dist: kiwisolver
Requires-Dist: lxml
Requires-Dist: matplotlib
Requires-Dist: numpy
Requires-Dist: openpyxl
Requires-Dist: packaging
Requires-Dist: pandas
Requires-Dist: pandas-flavor
Requires-Dist: patsy
Requires-Dist: pillow
Requires-Dist: pingouin
Requires-Dist: pyparsing
Requires-Dist: pyreadstat
Requires-Dist: python-dateutil
Requires-Dist: python-pptx
Requires-Dist: pytz
Requires-Dist: scikit-learn
Requires-Dist: scipy
Requires-Dist: seaborn
Requires-Dist: six
Requires-Dist: statsmodels
Requires-Dist: tabulate
Requires-Dist: threadpoolctl
Requires-Dist: typing_extensions
Requires-Dist: tzdata
Requires-Dist: xarray
Requires-Dist: XlsxWriter
Requires-Dist: pydantic
Requires-Dist: xlwings
Requires-Dist: openai
Requires-Dist: prince
Requires-Dist: kneed
Dynamic: license-file
